README.rst
setup.py
txtable/__init__.py
txtable/__main__.py
txtable/options_merger.py
txtable/table.py
txtable.egg-info/PKG-INFO
txtable.egg-info/SOURCES.txt
txtable.egg-info/dependency_links.txt
txtable.egg-info/top_level.txt
txtable/formatters/__init__.py
txtable/formatters/base_formatter.py
txtable/formatters/default_formatter.py
txtable/formatters/headless_formatter.py
txtable/formatters/md_formatter.py
txtable/formatters/rst_formatter.py