Metadata-Version: 1.0
Name: txtable
Version: 2.1.1
Summary: Plain text tables for Python 3
Home-page: https://github.com/atomgomba/txtable
Author: Károly Kiripolszky
Author-email: karcsi@ekezet.com
License: UNLICENSE
Platform: UNKNOWN
